LICENSE
README.md
setup.py
ontoim_py/__init__.py
ontoim_py/ns.py
ontoim_py.egg-info/PKG-INFO
ontoim_py.egg-info/SOURCES.txt
ontoim_py.egg-info/dependency_links.txt
ontoim_py.egg-info/requires.txt
ontoim_py.egg-info/top_level.txt
ontoim_py/ontoim/AccidentCircumstance.py
ontoim_py/ontoim/AccidentType.py
ontoim_py/ontoim/Accommodation.py
ontoim_py/ontoim/ArtisanOrganization.py
ontoim_py/ontoim/Association.py
ontoim_py/ontoim/AssociationCategory.py
ontoim_py/ontoim/Booking.py
ontoim_py/ontoim/Bookings.py
ontoim_py/ontoim/CadastralCategory.py
ontoim_py/ontoim/CadastralData.py
ontoim_py/ontoim/Citizens.py
ontoim_py/ontoim/CivilStatus.py
ontoim_py/ontoim/CivilStatusCategory.py
ontoim_py/ontoim/CivilStatusEvent.py
ontoim_py/ontoim/Classroom.py
ontoim_py/ontoim/CompanyDemographicCategory.py
ontoim_py/ontoim/ComprehensiveInstitute.py
ontoim_py/ontoim/Course.py
ontoim_py/ontoim/CulturalEvent.py
ontoim_py/ontoim/DemographicEvent.py
ontoim_py/ontoim/DemographicObservation.py
ontoim_py/ontoim/Employees.py
ontoim_py/ontoim/Event.py
ontoim_py/ontoim/Facility.py
ontoim_py/ontoim/GreenZone.py
ontoim_py/ontoim/Heritage.py
ontoim_py/ontoim/HeritageType.py
ontoim_py/ontoim/Hospital.py
ontoim_py/ontoim/HospitalDepartment.py
ontoim_py/ontoim/InvolvedEntity.py
ontoim_py/ontoim/InvolvedObstacle.py
ontoim_py/ontoim/InvolvedPerson.py
ontoim_py/ontoim/InvolvedPersonStatus.py
ontoim_py/ontoim/InvolvedVehicle.py
ontoim_py/ontoim/Members.py
ontoim_py/ontoim/Organization.py
ontoim_py/ontoim/OrganizationSection.py
ontoim_py/ontoim/PavementType.py
ontoim_py/ontoim/PhysicalClassroom.py
ontoim_py/ontoim/Plant.py
ontoim_py/ontoim/PlantHealthStatus.py
ontoim_py/ontoim/PlantStatusInTime.py
ontoim_py/ontoim/PrivateHospital.py
ontoim_py/ontoim/PrivateOrganization.py
ontoim_py/ontoim/PrivateSchool.py
ontoim_py/ontoim/PublicEvent.py
ontoim_py/ontoim/PublicHospital.py
ontoim_py/ontoim/PublicSchool.py
ontoim_py/ontoim/RevelationUnit.py
ontoim_py/ontoim/Road.py
ontoim_py/ontoim/RoadAccident.py
ontoim_py/ontoim/RoadCategory.py
ontoim_py/ontoim/RoadContext.py
ontoim_py/ontoim/RoadSegment.py
ontoim_py/ontoim/RoadSignal.py
ontoim_py/ontoim/RoadSignalPresence.py
