Metadata-Version: 2.1
Name: ontoim-py
Version: 0.0.5
Summary: A python package to create OntoIM RDFs.
Home-page: https://github.com/luca-martinelli-09/ontoim-py
Author: Luca Martinelli
Author-email: martinelliluca98@gmail.com
License: MIT
Keywords: ontoim,ontology,italianontology,rdf,graph
Platform: UNKNOWN
Classifier: Development Status :: 3 - Alpha
Classifier: Intended Audience :: Developers
Classifier: Environment :: Console
Classifier: Natural Language :: English
Classifier: License :: OSI Approved :: MIT License
Classifier: Programming Language :: Python :: 3
Classifier: Programming Language :: Python :: 3.7
Classifier: Programming Language :: Python :: 3.8
Classifier: Programming Language :: Python :: 3.9
Classifier: Programming Language :: Python :: 3.10
Requires-Python: >=3.7, <4
License-File: LICENSE
